marshaller/Makefile
marshaller/__init__.py
marshaller/cli.py
marshaller/tests/test_marshaller.py
marshaller-0.0.1.dist-info/METADATA
marshaller-0.0.1.dist-info/WHEEL
marshaller-0.0.1.dist-info/entry_points.txt
marshaller-0.0.1.dist-info/RECORD
